monaco_dash_editor/MonacoDashEditor.py
monaco_dash_editor/__init__.py
monaco_dash_editor/_imports_.py
monaco_dash_editor/async-null.js
monaco_dash_editor/async-null.js.map
monaco_dash_editor/metadata.json
monaco_dash_editor/monaco_dash_editor.min.js
monaco_dash_editor/monaco_dash_editor.min.js.map
monaco_dash_editor/package-info.json
monaco_dash_editor-0.0.2.dist-info/licenses/LICENSE
monaco_dash_editor-0.0.2.dist-info/METADATA
monaco_dash_editor-0.0.2.dist-info/WHEEL
monaco_dash_editor-0.0.2.dist-info/top_level.txt
monaco_dash_editor-0.0.2.dist-info/RECORD
