Metadata-Version: 2.4
Name: monaco_dash_editor
Version: 0.0.2
Summary: Monaco Editor for Dash
Author: Evan Rasmussen <evanras@umich.edu>
License: MIT
Classifier: Framework :: Dash
License-File: LICENSE
Dynamic: author
Dynamic: classifier
Dynamic: description
Dynamic: description-content-type
Dynamic: license
Dynamic: license-file
Dynamic: summary
